{"contracts/F1DataConnector.sol":{"jobHash":"solc-0_8_28-4f31c7a80d119ff8840d2bf006b0efa5813042fe","isolated":false,"artifactPaths":["C:\\Aditya\\flare-f1-bets\\artifacts\\contracts\\F1DataConnector.sol\\F1DataConnector.json"],"buildInfoPath":"C:\\Aditya\\flare-f1-bets\\artifacts\\build-info\\solc-0_8_28-7933e4959948f2e87aa1a438bfd7d93d0bea400f.json","buildInfoOutputPath":"C:\\Aditya\\flare-f1-bets\\artifacts\\build-info\\solc-0_8_28-7933e4959948f2e87aa1a438bfd7d93d0bea400f.output.json","typeFilePath":"C:\\Aditya\\flare-f1-bets\\artifacts\\contracts\\F1DataConnector.sol\\artifacts.d.ts","wasm":false},"contracts/FlareF1BetManager.sol":{"jobHash":"solc-0_8_28-1adef45c996d46030467bbf705bf18d338cd5dc3","isolated":false,"artifactPaths":["C:\\Aditya\\flare-f1-bets\\artifacts\\contracts\\FlareF1BetManager.sol\\FlareF1BetManager.json"],"buildInfoPath":"C:\\Aditya\\flare-f1-bets\\artifacts\\build-info\\solc-0_8_28-7933e4959948f2e87aa1a438bfd7d93d0bea400f.json","buildInfoOutputPath":"C:\\Aditya\\flare-f1-bets\\artifacts\\build-info\\solc-0_8_28-7933e4959948f2e87aa1a438bfd7d93d0bea400f.output.json","typeFilePath":"C:\\Aditya\\flare-f1-bets\\artifacts\\contracts\\FlareF1BetManager.sol\\artifacts.d.ts","wasm":false}}